videosplit/__init__.py
videosplit/videosplit.py
videosplit-0.4.1.dist-info/DESCRIPTION.rst
videosplit-0.4.1.dist-info/METADATA
videosplit-0.4.1.dist-info/RECORD
videosplit-0.4.1.dist-info/WHEEL
videosplit-0.4.1.dist-info/metadata.json
videosplit-0.4.1.dist-info/top_level.txt
