Metadata-Version: 2.0
Name: videosplit
Version: 0.4.1
Summary: Utility to extract frames out of a video
Home-page: UNKNOWN
Author: Johan Cervantes
License: UNKNOWN
Platform: UNKNOWN
Requires-Python: ==3.*
